handcric/__init__.py
handcric/handcric.py
handcric-0.0.5.dist-info/METADATA
handcric-0.0.5.dist-info/WHEEL
handcric-0.0.5.dist-info/top_level.txt
handcric-0.0.5.dist-info/RECORD
