Metadata-Version: 2.1
Name: handcric
Version: 0.0.5
Summary: terminal game of Hand Cricket
Home-page: UNKNOWN
Author: Chiranjeev Mishra(chirrumishra)
Author-email: chirrumishra@gmail.com
License: UNKNOWN
Keywords: match,python,cricket,hand cric,cricket lib
Platform: UNKNOWN
Classifier: Development Status :: 1 - Planning
Classifier: Intended Audience :: Developers
Classifier: Programming Language :: Python :: 3
Classifier: Operating System :: Unix
Classifier: Operating System :: MacOS :: MacOS X
Classifier: Operating System :: Microsoft :: Windows
